osgithub/__init__.py
osgithub/github.py
github_api_cache-0.1.0.dist-info/LICENSE
github_api_cache-0.1.0.dist-info/METADATA
github_api_cache-0.1.0.dist-info/WHEEL
github_api_cache-0.1.0.dist-info/top_level.txt
github_api_cache-0.1.0.dist-info/RECORD
