Metadata-Version: 2.1
Name: github-api-cache
Version: 0.1.0
Summary: UNKNOWN
Home-page: https://github.com/opensafely-core/github-api-cache
Author: OpenSAFELY
Author-email: tech@opensafely.org
License: UNKNOWN
Platform: UNKNOWN
Classifier: License :: OSI Approved :: GNU General Public License v3 (GPLv3)
Requires-Python: >=3.7
Requires-Dist: requests
Requires-Dist: requests-cache
Requires-Dist: furl
